[{"inputs":[{"indexed":true,"name":"_owner","internalType":"address","type":"address"},{"indexed":true,"name":"_approved","internalType":"address","type":"address"},{"indexed":true,"name":"_tokenId","internalType":"uint256","type":"uint256"}],"name":"Approval","anonymous":false,"type":"event"},{"inputs":[{"indexed":true,"name":"_owner","internalType":"address","type":"address"},{"indexed":true,"name":"_operator","internalType":"address","type":"address"},{"indexed":false,"name":"_approved","internalType":"bool","type":"bool"}],"name":"ApprovalForAll","anonymous":false,"type":"event"},{"inputs":[{"indexed":true,"name":"_from","internalType":"address","type":"address"},{"indexed":true,"name":"_to","internalType":"address","type":"address"},{"indexed":true,"name":"_tokenId","internalType":"uint256","type":"uint256"}],"name":"Transfer","anonymous":false,"type":"event"},{"outputs":[],"inputs":[{"name":"_approved","internalType":"address","type":"address"},{"name":"_tokenId","internalType":"uint256","type":"uint256"}],"name":"approve","stateMutability":"nonpayable","type":"function"},{"outputs":[{"name":"","internalType":"uint256","type":"uint256"}],"inputs":[{"name":"_owner","internalType":"address","type":"address"}],"name":"balanceOf","stateMutability":"view","type":"function"},{"outputs":[{"name":"","internalType":"address","type":"address"}],"inputs":[{"name":"_tokenId","internalType":"uint256","type":"uint256"}],"name":"getApproved","stateMutability":"view","type":"function"},{"outputs":[{"name":"","internalType":"bool","type":"bool"}],"inputs":[{"name":"_owner","internalType":"address","type":"address"},{"name":"_operator","internalType":"address","type":"address"}],"name":"isApprovedForAll","stateMutability":"view","type":"function"},{"outputs":[{"name":"","internalType":"address","type":"address"}],"inputs":[{"name":"_tokenId","internalType":"uint256","type":"uint256"}],"name":"ownerOf","stateMutability":"view","type":"function"},{"outputs":[],"inputs":[{"name":"_from","internalType":"address","type":"address"},{"name":"_to","internalType":"address","type":"address"},{"name":"_tokenId","internalType":"uint256","type":"uint256"}],"name":"safeTransferFrom","stateMutability":"nonpayable","type":"function"},{"outputs":[],"inputs":[{"name":"_from","internalType":"address","type":"address"},{"name":"_to","internalType":"address","type":"address"},{"name":"_tokenId","internalType":"uint256","type":"uint256"},{"name":"data","internalType":"bytes","type":"bytes"}],"name":"safeTransferFrom","stateMutability":"nonpayable","type":"function"},{"outputs":[],"inputs":[{"name":"_operator","internalType":"address","type":"address"},{"name":"_approved","internalType":"bool","type":"bool"}],"name":"setApprovalForAll","stateMutability":"nonpayable","type":"function"},{"outputs":[],"inputs":[{"name":"_from","internalType":"address","type":"address"},{"name":"_to","internalType":"address","type":"address"},{"name":"_tokenId","internalType":"uint256","type":"uint256"}],"name":"transferFrom","stateMutability":"nonpayable","type":"function"}]